bin/__init__.py
bin/generate-ethereum-networks.py
bin/generate-network-init.py
bin/script_utils.py
bin/search_checklocktimeverify.py
bin/set_bitcoin_related_network_params.py
bin/test-audit-contract.py
bin/test-extract-secret.py
bin/test-initial-transaction.py
bin/test-networks.py
bin/test-participate-transaction.py
bin/test-redeem-transaction.py
bin/test-refund-transaction.py
clove/__init__.py
clove/constants.py
clove/exceptions.py
clove/block_explorer/__init__.py
clove/block_explorer/base.py
clove/block_explorer/blockcypher.py
clove/block_explorer/cryptoid.py
clove/block_explorer/etherscan.py
clove/block_explorer/insight.py
clove/network/__init__.py
clove/network/base.py
clove/network/bitcoin/__init__.py
clove/network/bitcoin/base.py
clove/network/bitcoin/contract.py
clove/network/bitcoin/transaction.py
clove/network/bitcoin/utxo.py
clove/network/bitcoin/wallet.py
clove/network/bitcoin_based/__init__.py
clove/network/bitcoin_based/aquariuscoin.py
clove/network/bitcoin_based/audiocoin.py
clove/network/bitcoin_based/bata.py
clove/network/bitcoin_based/bitcoin_cash.py
clove/network/bitcoin_based/bitcoin_gold.py
clove/network/bitcoin_based/bitcore.py
clove/network/bitcoin_based/bitmark.py
clove/network/bitcoin_based/bitsend.py
clove/network/bitcoin_based/blackcoin.py
clove/network/bitcoin_based/blocknet.py
clove/network/bitcoin_based/creativecoin.py
clove/network/bitcoin_based/dash.py
clove/network/bitcoin_based/digibyte.py
clove/network/bitcoin_based/dopecoin.py
clove/network/bitcoin_based/egulden.py
clove/network/bitcoin_based/eternity.py
clove/network/bitcoin_based/europecoin.py
clove/network/bitcoin_based/goldcoin.py
clove/network/bitcoin_based/greencoin.py
clove/network/bitcoin_based/guncoin.py
clove/network/bitcoin_based/i0coin.py
clove/network/bitcoin_based/ivc_coin.py
clove/network/bitcoin_based/joulecoin.py
clove/network/bitcoin_based/komodo.py
clove/network/bitcoin_based/lanacoin.py
clove/network/bitcoin_based/litecoin.py
clove-1.2.16.dist-info/LICENSE.md
clove-1.2.16.dist-info/METADATA
clove-1.2.16.dist-info/WHEEL
clove-1.2.16.dist-info/top_level.txt
clove-1.2.16.dist-info/RECORD
